{
	"format_version": "1.9.0",
	"credit": "Made with Blockbench",
	"texture_size": [64, 64],
	"textures": {
		"0": "meowstorage:block/small_backpack_texture",
		"particle": "meowstorage:block/small_backpack_texture"
	},
	"elements": [
		{
			"from": [4, 6, 2],
			"to": [12, 11, 8],
			"rotation": {"angle": 0, "axis": "y", "origin": [4, 7, 2]},
			"faces": {
				"north": {"uv": [3.75, 4.5, 5.75, 5.75], "texture": "#0"},
				"east": {"uv": [5, 0, 6.5, 1.25], "texture": "#0"},
				"south": {"uv": [0, 5, 2, 6.25], "texture": "#0"},
				"west": {"uv": [5, 1.25, 6.5, 2.5], "texture": "#0"},
				"up": {"uv": [4.5, 4.5, 2.5, 3], "texture": "#0"},
				"down": {"uv": [2, 3.5, 0, 5], "texture": "#0"}
			}
		},
		{
			"from": [3, 0, 2],
			"to": [13, 6, 9],
			"rotation": {"angle": 0, "axis": "y", "origin": [7, 0, 2]},
			"faces": {
				"north": {"uv": [2.5, 0, 5, 1.5], "texture": "#0"},
				"east": {"uv": [2, 4.5, 3.75, 6], "texture": "#0"},
				"south": {"uv": [2.5, 1.5, 5, 3], "texture": "#0"},
				"west": {"uv": [4.5, 3, 6.25, 4.5], "texture": "#0"},
				"up": {"uv": [2.5, 1.75, 0, 0], "texture": "#0"},
				"down": {"uv": [2.5, 1.75, 0, 3.5], "texture": "#0"}
			}
		},
		{
			"from": [10, 0, 1],
			"to": [12, 11, 2],
			"rotation": {"angle": 0, "axis": "y", "origin": [10, 0, 0]},
			"faces": {
				"north": {"uv": [3.75, 5.75, 4.25, 8.5], "texture": "#0"},
				"east": {"uv": [5.25, 5.75, 5.5, 8.5], "texture": "#0"},
				"south": {"uv": [4.25, 5.75, 4.75, 8.5], "texture": "#0"},
				"west": {"uv": [5.5, 5.75, 5.75, 8.5], "texture": "#0"},
				"up": {"uv": [2.5, 3.75, 2, 3.5], "texture": "#0"},
				"down": {"uv": [2.5, 3.75, 2, 4], "texture": "#0"}
			}
		},
		{
			"from": [4, 0, 1],
			"to": [6, 11, 2],
			"rotation": {"angle": 0, "axis": "y", "origin": [4, 0, 0]},
			"faces": {
				"north": {"uv": [5.75, 4.5, 6.25, 7.25], "texture": "#0"},
				"east": {"uv": [2, 6, 2.25, 8.75], "texture": "#0"},
				"south": {"uv": [4.75, 5.75, 5.25, 8.5], "texture": "#0"},
				"west": {"uv": [2.25, 6, 2.5, 8.75], "texture": "#0"},
				"up": {"uv": [2.5, 4.25, 2, 4], "texture": "#0"},
				"down": {"uv": [2.5, 4.25, 2, 4.5], "texture": "#0"}
			}
		},
		{
			"from": [6, 11, 4],
			"to": [7, 13, 5],
			"rotation": {"angle": 0, "axis": "y", "origin": [5, 11, 3]},
			"faces": {
				"north": {"uv": [5, 2.5, 5.25, 3], "texture": "#0"},
				"east": {"uv": [5.25, 2.5, 5.5, 3], "texture": "#0"},
				"south": {"uv": [5.5, 2.5, 5.75, 3], "texture": "#0"},
				"west": {"uv": [5.75, 2.5, 6, 3], "texture": "#0"},
				"up": {"uv": [2, 6.5, 1.75, 6.25], "texture": "#0"},
				"down": {"uv": [6.5, 4, 6.25, 4.25], "texture": "#0"}
			}
		},
		{
			"from": [7, 12, 4],
			"to": [9, 13, 5],
			"rotation": {"angle": 0, "axis": "y", "origin": [7, 11, 3]},
			"faces": {
				"north": {"uv": [2.5, 6, 3, 6.25], "texture": "#0"},
				"east": {"uv": [6.25, 4.25, 6.5, 4.5], "texture": "#0"},
				"south": {"uv": [6, 2.5, 6.5, 2.75], "texture": "#0"},
				"west": {"uv": [6.25, 4.5, 6.5, 4.75], "texture": "#0"},
				"up": {"uv": [6.5, 3, 6, 2.75], "texture": "#0"},
				"down": {"uv": [3.5, 6, 3, 6.25], "texture": "#0"}
			}
		},
		{
			"from": [9, 11, 4],
			"to": [10, 13, 5],
			"rotation": {"angle": 0, "axis": "y", "origin": [8, 11, 3]},
			"faces": {
				"north": {"uv": [3.5, 6, 3.75, 6.5], "texture": "#0"},
				"east": {"uv": [0, 6.25, 0.25, 6.75], "texture": "#0"},
				"south": {"uv": [0.25, 6.25, 0.5, 6.75], "texture": "#0"},
				"west": {"uv": [0.5, 6.25, 0.75, 6.75], "texture": "#0"},
				"up": {"uv": [6.5, 5, 6.25, 4.75], "texture": "#0"},
				"down": {"uv": [6.5, 5, 6.25, 5.25], "texture": "#0"}
			}
		},
		{
			"from": [5, 8, 7.5],
			"to": [7, 9, 8.5],
			"rotation": {"angle": 0, "axis": "y", "origin": [5, 7, 6.5]},
			"faces": {
				"north": {"uv": [0.75, 6.25, 1.25, 6.5], "texture": "#0"},
				"east": {"uv": [6.25, 5.25, 6.5, 5.5], "texture": "#0"},
				"south": {"uv": [1.25, 6.25, 1.75, 6.5], "texture": "#0"},
				"west": {"uv": [6.25, 5.5, 6.5, 5.75], "texture": "#0"},
				"up": {"uv": [3, 6.5, 2.5, 6.25], "texture": "#0"},
				"down": {"uv": [3.5, 6.25, 3, 6.5], "texture": "#0"}
			}
		},
		{
			"from": [5, 3, 8.5],
			"to": [7, 4, 9.5],
			"rotation": {"angle": 0, "axis": "y", "origin": [5, 2, 7.5]},
			"faces": {
				"north": {"uv": [6.25, 3, 6.75, 3.25], "texture": "#0"},
				"east": {"uv": [6.25, 5.75, 6.5, 6], "texture": "#0"},
				"south": {"uv": [6.25, 3.25, 6.75, 3.5], "texture": "#0"},
				"west": {"uv": [6.25, 6, 6.5, 6.25], "texture": "#0"},
				"up": {"uv": [6.75, 3.75, 6.25, 3.5], "texture": "#0"},
				"down": {"uv": [6.75, 3.75, 6.25, 4], "texture": "#0"}
			}
		}
	],
	"display": {
		"thirdperson_righthand": {
			"rotation": [-140.73, 80.39, -152.1],
			"translation": [3.5, -2.25, -4]
		},
		"thirdperson_lefthand": {
			"rotation": [-140.73, 80.39, -152.1],
			"translation": [3.5, -2.25, -4]
		},
		"ground": {
			"translation": [0, 5.5, 0]
		},
		"gui": {
			"rotation": [20, -20, 0],
			"translation": [-0.75, 1, 0]
		},
		"head": {
			"rotation": [0, 180, 0],
			"translation": [0, 14.5, 0]
		},
		"fixed": {
			"rotation": [0, -180, 0],
			"translation": [0, 0, -4.75]
		}
	},
	"groups": [
		{
			"name": "backpack",
			"origin": [4, 7, 2],
			"color": 0,
			"children": [0, 1]
		},
		{
			"name": "straps",
			"origin": [10, 0, 0],
			"color": 0,
			"children": [2, 3]
		},
		{
			"name": "handle",
			"origin": [5, 11, 3],
			"color": 0,
			"children": [4, 5, 6]
		},
		{
			"name": "zippers",
			"origin": [5, 7, 6.5],
			"color": 0,
			"children": [7, 8]
		}
	]
}